streamlit_music_score/__init__.py
streamlit_music_score-1.0.0.dist-info/licenses/LICENSE
streamlit_music_score-1.0.0.dist-info/METADATA
streamlit_music_score-1.0.0.dist-info/WHEEL
streamlit_music_score-1.0.0.dist-info/top_level.txt
streamlit_music_score-1.0.0.dist-info/RECORD
