Metadata-Version: 2.4
Name: streamlit-music-score
Version: 1.0.0
Summary: Streamlit helper to render MusicXML scores using OpenSheetMusicDisplay
Author-email: David Issa Mattos <issamattos.david@gmail.com>
License: MIT License
Project-URL: Homepage, https://github.com/davidissamattos/streamlit-music-score
Requires-Python: >=3.9
License-File: LICENSE
Requires-Dist: streamlit>=1.32
Requires-Dist: music21>=9.1.0
Dynamic: license-file
